{
  "bleauprint": {
    "images": [
      "https://storage.googleapis.com/portfoliosite-9335f.appspot.com/bleauprint%2Fimages%2Fimage0.webp",
      "https://storage.googleapis.com/portfoliosite-9335f.appspot.com/bleauprint%2Fimages%2Fimage1.webp",
      "https://storage.googleapis.com/portfoliosite-9335f.appspot.com/bleauprint%2Fimages%2Fimage2.webp",
      "https://storage.googleapis.com/portfoliosite-9335f.appspot.com/bleauprint%2Fimages%2Fimage3.webp",
      "https://storage.googleapis.com/portfoliosite-9335f.appspot.com/bleauprint%2Fimages%2Fimage4.webp"
    ],
    "tile": "https://storage.googleapis.com/portfoliosite-9335f.appspot.com/bleauprint%2Ftile.webp"
  },
  "cheerio": {
    "images": [
      "https://storage.googleapis.com/portfoliosite-9335f.appspot.com/cheerio%2Fimages%2Fimage0.png",
      "https://storage.googleapis.com/portfoliosite-9335f.appspot.com/cheerio%2Fimages%2Fimage1.png",
      "https://storage.googleapis.com/portfoliosite-9335f.appspot.com/cheerio%2Fimages%2Fimage2.png",
      "https://storage.googleapis.com/portfoliosite-9335f.appspot.com/cheerio%2Fimages%2Fimage3.png",
      "https://storage.googleapis.com/portfoliosite-9335f.appspot.com/cheerio%2Fimages%2Fimage4.png",
      "https://storage.googleapis.com/portfoliosite-9335f.appspot.com/cheerio%2Fimages%2Fimage5.png",
      "https://storage.googleapis.com/portfoliosite-9335f.appspot.com/cheerio%2Fimages%2Fimage6.png"
    ],
    "tile": "https://storage.googleapis.com/portfoliosite-9335f.appspot.com/cheerio%2Ftile.png"
  },
  "elaj": {
    "images": [
      "https://storage.googleapis.com/portfoliosite-9335f.appspot.com/elaj%2Fimages%2Fimage0.png",
      "https://storage.googleapis.com/portfoliosite-9335f.appspot.com/elaj%2Fimages%2Fimage1.png",
      "https://storage.googleapis.com/portfoliosite-9335f.appspot.com/elaj%2Fimages%2Fimage2.png",
      "https://storage.googleapis.com/portfoliosite-9335f.appspot.com/elaj%2Fimages%2Fimage3.png",
      "https://storage.googleapis.com/portfoliosite-9335f.appspot.com/elaj%2Fimages%2Fimage4.png"
    ],
    "tile": "https://storage.googleapis.com/portfoliosite-9335f.appspot.com/elaj%2Ftile.png"
  },
  "event_tracker": {
    "images": [
      "https://storage.googleapis.com/portfoliosite-9335f.appspot.com/event_tracker%2Fimages%2Fimage0.png",
      "https://storage.googleapis.com/portfoliosite-9335f.appspot.com/event_tracker%2Fimages%2Fimage1.png",
      "https://storage.googleapis.com/portfoliosite-9335f.appspot.com/event_tracker%2Fimages%2Fimage2.png",
      "https://storage.googleapis.com/portfoliosite-9335f.appspot.com/event_tracker%2Fimages%2Fimage3.png",
      "https://storage.googleapis.com/portfoliosite-9335f.appspot.com/event_tracker%2Fimages%2Fimage4.png",
      "https://storage.googleapis.com/portfoliosite-9335f.appspot.com/event_tracker%2Fimages%2Fimage5.png",
      "https://storage.googleapis.com/portfoliosite-9335f.appspot.com/event_tracker%2Fimages%2Fimage6.png",
      "https://storage.googleapis.com/portfoliosite-9335f.appspot.com/event_tracker%2Fimages%2Fimage7.png",
      "https://storage.googleapis.com/portfoliosite-9335f.appspot.com/event_tracker%2Fimages%2Fimage8.png"
    ],
    "tile": "https://storage.googleapis.com/portfoliosite-9335f.appspot.com/event_tracker%2Ftile.png"
  },
  "filter_alpha": {
    "images": [
      "https://storage.googleapis.com/portfoliosite-9335f.appspot.com/filter_alpha%2Fimages%2Fimage0.png",
      "https://storage.googleapis.com/portfoliosite-9335f.appspot.com/filter_alpha%2Fimages%2Fimage1.png",
      "https://storage.googleapis.com/portfoliosite-9335f.appspot.com/filter_alpha%2Fimages%2Fimage2.png",
      "https://storage.googleapis.com/portfoliosite-9335f.appspot.com/filter_alpha%2Fimages%2Fimage3.png",
      "https://storage.googleapis.com/portfoliosite-9335f.appspot.com/filter_alpha%2Fimages%2Fimage4.png"
    ],
    "mobile": [
      "https://storage.googleapis.com/portfoliosite-9335f.appspot.com/filter_alpha%2Fmobile%2Fimage0.png",
      "https://storage.googleapis.com/portfoliosite-9335f.appspot.com/filter_alpha%2Fmobile%2Fimage1.png",
      "https://storage.googleapis.com/portfoliosite-9335f.appspot.com/filter_alpha%2Fmobile%2Fimage2.png",
      "https://storage.googleapis.com/portfoliosite-9335f.appspot.com/filter_alpha%2Fmobile%2Fimage3.png",
      "https://storage.googleapis.com/portfoliosite-9335f.appspot.com/filter_alpha%2Fmobile%2Fimage4.png"
    ],
    "tile": "https://storage.googleapis.com/portfoliosite-9335f.appspot.com/filter_alpha%2Ftile.png"
  },
  "ghirasti": {
    "images": [
      "https://storage.googleapis.com/portfoliosite-9335f.appspot.com/ghirasti%2Fimages%2Fimage0.png",
      "https://storage.googleapis.com/portfoliosite-9335f.appspot.com/ghirasti%2Fimages%2Fimage1.png",
      "https://storage.googleapis.com/portfoliosite-9335f.appspot.com/ghirasti%2Fimages%2Fimage2.png",
      "https://storage.googleapis.com/portfoliosite-9335f.appspot.com/ghirasti%2Fimages%2Fimage3.png"
    ],
    "tile": "https://storage.googleapis.com/portfoliosite-9335f.appspot.com/ghirasti%2Ftile.png"
  },
  "healthcare_chatbot": {
    "images": [
      "https://storage.googleapis.com/portfoliosite-9335f.appspot.com/healthcare_chatbot%2Fimages%2Fimage0.png",
      "https://storage.googleapis.com/portfoliosite-9335f.appspot.com/healthcare_chatbot%2Fimages%2Fimage1.png",
      "https://storage.googleapis.com/portfoliosite-9335f.appspot.com/healthcare_chatbot%2Fimages%2Fimage2.png",
      "https://storage.googleapis.com/portfoliosite-9335f.appspot.com/healthcare_chatbot%2Fimages%2Fimage3.png",
      "https://storage.googleapis.com/portfoliosite-9335f.appspot.com/healthcare_chatbot%2Fimages%2Fimage4.png",
      "https://storage.googleapis.com/portfoliosite-9335f.appspot.com/healthcare_chatbot%2Fimages%2Fimage5.png",
      "https://storage.googleapis.com/portfoliosite-9335f.appspot.com/healthcare_chatbot%2Fimages%2Fimage6.png"
    ],
    "tile": "https://storage.googleapis.com/portfoliosite-9335f.appspot.com/healthcare_chatbot%2Ftile.png"
  },
  "injalink": {
    "images": [
      "https://storage.googleapis.com/portfoliosite-9335f.appspot.com/injalink%2Fimages%2Fimage0.png",
      "https://storage.googleapis.com/portfoliosite-9335f.appspot.com/injalink%2Fimages%2Fimage1.png",
      "https://storage.googleapis.com/portfoliosite-9335f.appspot.com/injalink%2Fimages%2Fimage2.png",
      "https://storage.googleapis.com/portfoliosite-9335f.appspot.com/injalink%2Fimages%2Fimage3.png",
      "https://storage.googleapis.com/portfoliosite-9335f.appspot.com/injalink%2Fimages%2Fimage4.png",
      "https://storage.googleapis.com/portfoliosite-9335f.appspot.com/injalink%2Fimages%2Fimage5.png",
      "https://storage.googleapis.com/portfoliosite-9335f.appspot.com/injalink%2Fimages%2Fimage6.png"
    ],
    "tile": "https://storage.googleapis.com/portfoliosite-9335f.appspot.com/injalink%2Ftile.png"
  },
  "insidartours": {
    "images": [
      "https://storage.googleapis.com/portfoliosite-9335f.appspot.com/insidartours%2Fimages%2Fimage0.png",
      "https://storage.googleapis.com/portfoliosite-9335f.appspot.com/insidartours%2Fimages%2Fimage1.png",
      "https://storage.googleapis.com/portfoliosite-9335f.appspot.com/insidartours%2Fimages%2Fimage2.png",
      "https://storage.googleapis.com/portfoliosite-9335f.appspot.com/insidartours%2Fimages%2Fimage3.png",
      "https://storage.googleapis.com/portfoliosite-9335f.appspot.com/insidartours%2Fimages%2Fimage4.png",
      "https://storage.googleapis.com/portfoliosite-9335f.appspot.com/insidartours%2Fimages%2Fimage5.png"
    ],
    "mobile": [
      "https://storage.googleapis.com/portfoliosite-9335f.appspot.com/insidartours%2Fmobile%2Fimage0.png",
      "https://storage.googleapis.com/portfoliosite-9335f.appspot.com/insidartours%2Fmobile%2Fimage1.png",
      "https://storage.googleapis.com/portfoliosite-9335f.appspot.com/insidartours%2Fmobile%2Fimage2.png",
      "https://storage.googleapis.com/portfoliosite-9335f.appspot.com/insidartours%2Fmobile%2Fimage3.png",
      "https://storage.googleapis.com/portfoliosite-9335f.appspot.com/insidartours%2Fmobile%2Fimage4.png",
      "https://storage.googleapis.com/portfoliosite-9335f.appspot.com/insidartours%2Fmobile%2Fimage5.png"
    ],
    "tile": "https://storage.googleapis.com/portfoliosite-9335f.appspot.com/insidartours%2Ftile.png"
  },
  "inventory_tracker": {
    "images": [
      "https://storage.googleapis.com/portfoliosite-9335f.appspot.com/inventory_tracker%2Fimages%2Fimage0.png",
      "https://storage.googleapis.com/portfoliosite-9335f.appspot.com/inventory_tracker%2Fimages%2Fimage1.png",
      "https://storage.googleapis.com/portfoliosite-9335f.appspot.com/inventory_tracker%2Fimages%2Fimage2.png",
      "https://storage.googleapis.com/portfoliosite-9335f.appspot.com/inventory_tracker%2Fimages%2Fimage3.png",
      "https://storage.googleapis.com/portfoliosite-9335f.appspot.com/inventory_tracker%2Fimages%2Fimage4.png",
      "https://storage.googleapis.com/portfoliosite-9335f.appspot.com/inventory_tracker%2Fimages%2Fimage5.png"
    ],
    "mobile": [
      "https://storage.googleapis.com/portfoliosite-9335f.appspot.com/inventory_tracker%2Fmobile%2Fimage0.png",
      "https://storage.googleapis.com/portfoliosite-9335f.appspot.com/inventory_tracker%2Fmobile%2Fimage1.png",
      "https://storage.googleapis.com/portfoliosite-9335f.appspot.com/inventory_tracker%2Fmobile%2Fimage2.png",
      "https://storage.googleapis.com/portfoliosite-9335f.appspot.com/inventory_tracker%2Fmobile%2Fimage3.png",
      "https://storage.googleapis.com/portfoliosite-9335f.appspot.com/inventory_tracker%2Fmobile%2Fimage4.png"
    ],
    "tile": "https://storage.googleapis.com/portfoliosite-9335f.appspot.com/inventory_tracker%2Ftile.png"
  },
  "iran_top5": {
    "images": [
      "https://storage.googleapis.com/portfoliosite-9335f.appspot.com/iran_top5%2Fimages%2Fimage0.png",
      "https://storage.googleapis.com/portfoliosite-9335f.appspot.com/iran_top5%2Fimages%2Fimage1.png",
      "https://storage.googleapis.com/portfoliosite-9335f.appspot.com/iran_top5%2Fimages%2Fimage10.png",
      "https://storage.googleapis.com/portfoliosite-9335f.appspot.com/iran_top5%2Fimages%2Fimage11.png",
      "https://storage.googleapis.com/portfoliosite-9335f.appspot.com/iran_top5%2Fimages%2Fimage2.png",
      "https://storage.googleapis.com/portfoliosite-9335f.appspot.com/iran_top5%2Fimages%2Fimage3.png",
      "https://storage.googleapis.com/portfoliosite-9335f.appspot.com/iran_top5%2Fimages%2Fimage4.png",
      "https://storage.googleapis.com/portfoliosite-9335f.appspot.com/iran_top5%2Fimages%2Fimage5.png",
      "https://storage.googleapis.com/portfoliosite-9335f.appspot.com/iran_top5%2Fimages%2Fimage6.png",
      "https://storage.googleapis.com/portfoliosite-9335f.appspot.com/iran_top5%2Fimages%2Fimage7.png",
      "https://storage.googleapis.com/portfoliosite-9335f.appspot.com/iran_top5%2Fimages%2Fimage8.png",
      "https://storage.googleapis.com/portfoliosite-9335f.appspot.com/iran_top5%2Fimages%2Fimage9.png"
    ],
    "mobile": [
      "https://storage.googleapis.com/portfoliosite-9335f.appspot.com/iran_top5%2Fmobile%2Fimage0.png",
      "https://storage.googleapis.com/portfoliosite-9335f.appspot.com/iran_top5%2Fmobile%2Fimage1.png",
      "https://storage.googleapis.com/portfoliosite-9335f.appspot.com/iran_top5%2Fmobile%2Fimage2.png",
      "https://storage.googleapis.com/portfoliosite-9335f.appspot.com/iran_top5%2Fmobile%2Fimage3.png",
      "https://storage.googleapis.com/portfoliosite-9335f.appspot.com/iran_top5%2Fmobile%2Fimage4.png",
      "https://storage.googleapis.com/portfoliosite-9335f.appspot.com/iran_top5%2Fmobile%2Fimage5.png"
    ],
    "tile": "https://storage.googleapis.com/portfoliosite-9335f.appspot.com/iran_top5%2Ftile.png"
  },
  "journal_app": {
    "images": [
      "https://storage.googleapis.com/portfoliosite-9335f.appspot.com/journal_app%2Fimages%2Fimage0.png",
      "https://storage.googleapis.com/portfoliosite-9335f.appspot.com/journal_app%2Fimages%2Fimage1.png",
      "https://storage.googleapis.com/portfoliosite-9335f.appspot.com/journal_app%2Fimages%2Fimage2.png",
      "https://storage.googleapis.com/portfoliosite-9335f.appspot.com/journal_app%2Fimages%2Fimage3.png",
      "https://storage.googleapis.com/portfoliosite-9335f.appspot.com/journal_app%2Fimages%2Fimage4.png",
      "https://storage.googleapis.com/portfoliosite-9335f.appspot.com/journal_app%2Fimages%2Fimage5.png",
      "https://storage.googleapis.com/portfoliosite-9335f.appspot.com/journal_app%2Fimages%2Fimage6.png",
      "https://storage.googleapis.com/portfoliosite-9335f.appspot.com/journal_app%2Fimages%2Fimage7.png"
    ],
    "tile": "https://storage.googleapis.com/portfoliosite-9335f.appspot.com/journal_app%2Ftile.png"
  },
  "lahore_covid_visualization": {
    "images": [
      "https://storage.googleapis.com/portfoliosite-9335f.appspot.com/lahore_covid_visualization%2Fimages%2Fimage0.png",
      "https://storage.googleapis.com/portfoliosite-9335f.appspot.com/lahore_covid_visualization%2Fimages%2Fimage1.png",
      "https://storage.googleapis.com/portfoliosite-9335f.appspot.com/lahore_covid_visualization%2Fimages%2Fimage2.png",
      "https://storage.googleapis.com/portfoliosite-9335f.appspot.com/lahore_covid_visualization%2Fimages%2Fimage3.png",
      "https://storage.googleapis.com/portfoliosite-9335f.appspot.com/lahore_covid_visualization%2Fimages%2Fimage4.png",
      "https://storage.googleapis.com/portfoliosite-9335f.appspot.com/lahore_covid_visualization%2Fimages%2Fimage5.png"
    ],
    "tile": "https://storage.googleapis.com/portfoliosite-9335f.appspot.com/lahore_covid_visualization%2Ftile.png"
  },
  "music_app": {
    "images": [
      "https://storage.googleapis.com/portfoliosite-9335f.appspot.com/music_app%2Fimages%2Fimage0.png",
      "https://storage.googleapis.com/portfoliosite-9335f.appspot.com/music_app%2Fimages%2Fimage1.png",
      "https://storage.googleapis.com/portfoliosite-9335f.appspot.com/music_app%2Fimages%2Fimage2.png",
      "https://storage.googleapis.com/portfoliosite-9335f.appspot.com/music_app%2Fimages%2Fimage3.png",
      "https://storage.googleapis.com/portfoliosite-9335f.appspot.com/music_app%2Fimages%2Fimage4.png",
      "https://storage.googleapis.com/portfoliosite-9335f.appspot.com/music_app%2Fimages%2Fimage5.png",
      "https://storage.googleapis.com/portfoliosite-9335f.appspot.com/music_app%2Fimages%2Fimage6.png",
      "https://storage.googleapis.com/portfoliosite-9335f.appspot.com/music_app%2Fimages%2Fimage7.png",
      "https://storage.googleapis.com/portfoliosite-9335f.appspot.com/music_app%2Fimages%2Fimage8.png",
      "https://storage.googleapis.com/portfoliosite-9335f.appspot.com/music_app%2Fimages%2Fimage9.png"
    ],
    "tile": "https://storage.googleapis.com/portfoliosite-9335f.appspot.com/music_app%2Ftile.png"
  },
  "orfol": {
    "images": [
      "https://storage.googleapis.com/portfoliosite-9335f.appspot.com/orfol%2Fimages%2Fimage0.png",
      "https://storage.googleapis.com/portfoliosite-9335f.appspot.com/orfol%2Fimages%2Fimage1.png",
      "https://storage.googleapis.com/portfoliosite-9335f.appspot.com/orfol%2Fimages%2Fimage2.png",
      "https://storage.googleapis.com/portfoliosite-9335f.appspot.com/orfol%2Fimages%2Fimage3.png",
      "https://storage.googleapis.com/portfoliosite-9335f.appspot.com/orfol%2Fimages%2Fimage4.png",
      "https://storage.googleapis.com/portfoliosite-9335f.appspot.com/orfol%2Fimages%2Fimage5.png",
      "https://storage.googleapis.com/portfoliosite-9335f.appspot.com/orfol%2Fimages%2Fimage6.png"
    ],
    "tile": "https://storage.googleapis.com/portfoliosite-9335f.appspot.com/orfol%2Ftile.png"
  },
  "roam": {
    "images": [
      "https://storage.googleapis.com/portfoliosite-9335f.appspot.com/roam%2Fimages%2Fimage0.png",
      "https://storage.googleapis.com/portfoliosite-9335f.appspot.com/roam%2Fimages%2Fimage1.png",
      "https://storage.googleapis.com/portfoliosite-9335f.appspot.com/roam%2Fimages%2Fimage10.png",
      "https://storage.googleapis.com/portfoliosite-9335f.appspot.com/roam%2Fimages%2Fimage11.png",
      "https://storage.googleapis.com/portfoliosite-9335f.appspot.com/roam%2Fimages%2Fimage12.png",
      "https://storage.googleapis.com/portfoliosite-9335f.appspot.com/roam%2Fimages%2Fimage2.png",
      "https://storage.googleapis.com/portfoliosite-9335f.appspot.com/roam%2Fimages%2Fimage3.png",
      "https://storage.googleapis.com/portfoliosite-9335f.appspot.com/roam%2Fimages%2Fimage4.png",
      "https://storage.googleapis.com/portfoliosite-9335f.appspot.com/roam%2Fimages%2Fimage5.png",
      "https://storage.googleapis.com/portfoliosite-9335f.appspot.com/roam%2Fimages%2Fimage6.png",
      "https://storage.googleapis.com/portfoliosite-9335f.appspot.com/roam%2Fimages%2Fimage7.png",
      "https://storage.googleapis.com/portfoliosite-9335f.appspot.com/roam%2Fimages%2Fimage8.png",
      "https://storage.googleapis.com/portfoliosite-9335f.appspot.com/roam%2Fimages%2Fimage9.png"
    ],
    "tile": "https://storage.googleapis.com/portfoliosite-9335f.appspot.com/roam%2Ftile.png"
  },
  "stock_availability": {
    "images": [
      "https://storage.googleapis.com/portfoliosite-9335f.appspot.com/stock_availability%2Fimages%2Fimage0.png",
      "https://storage.googleapis.com/portfoliosite-9335f.appspot.com/stock_availability%2Fimages%2Fimage1.png",
      "https://storage.googleapis.com/portfoliosite-9335f.appspot.com/stock_availability%2Fimages%2Fimage2.png",
      "https://storage.googleapis.com/portfoliosite-9335f.appspot.com/stock_availability%2Fimages%2Fimage3.png"
    ],
    "tile": "https://storage.googleapis.com/portfoliosite-9335f.appspot.com/stock_availability%2Ftile.png"
  }
}